Metadata-Version: 2.4
Name: apipeline
Version: 0.2.7
Summary: Python pipeline with asyncio support
Home-page: https://github.com/weedge/pipeline-py
Author: weedge
Author-email: weege007@gmail.com
License: BSD 3-Clause
Project-URL: Changes, https://github.com/weedge/pipeline-py/releases
Project-URL: Code, https://github.com/weedge/pipeline-py
Project-URL: Issue tracker, https://github.com/weedge/pipeline-py/issues
Keywords: pipeline,asyncio
Requires-Python: >=3.10
License-File: LICENSE
Requires-Dist: pydantic>=2.8.2
Dynamic: author
Dynamic: author-email
Dynamic: description
Dynamic: description-content-type
Dynamic: home-page
Dynamic: keywords
Dynamic: license
Dynamic: license-file
Dynamic: project-url
Dynamic: requires-dist
Dynamic: requires-python
Dynamic: summary
